<?xml version="1.0" encoding="UTF-8" standalone="no"?>
<event category="KEYPRESS" id="27">
  <actions>
    <action id="603" library="1">
      <!--action name: Code-->
      <kind>CODE</kind>
      <allowRelative>false</allowRelative>
      <question>false</question>
      <canApplyTo>true</canApplyTo>
      <actionType>CODE</actionType>
      <functionName/>
      <relative>false</relative>
      <not>false</not>
      <appliesTo>.self</appliesTo>
      <arguments>
        <argument kind="STRING">if(!instance_exists(InGameMenuController) &amp;&amp; !instance_exists(OptionsController) &amp;&amp; !instance_exists(ControlsController))
 &amp;&amp; !instance_exists(HUDOptionsController) {
    instance_create(x,y,InGameMenuController);
}
</argument>
      </arguments>
    </action>
  </actions>
</event>
