<?xml version="1.0" encoding="UTF-8" standalone="no"?>
<room>
  <caption/>
  <size height="1956" width="6204"/>
  <grid>
    <isometric>false</isometric>
    <snap x="6" y="6"/>
  </grid>
  <speed>30</speed>
  <persistent>false</persistent>
  <creationCode>basicRoomSetup();
instance_create(0,0,WaterwayO);</creationCode>
  <backgroundColor>000000</backgroundColor>
  <drawBackgroundColor>true</drawBackgroundColor>
  <backgrounds>
    <backgroundDef>
      <visibleOnRoomStart>true</visibleOnRoomStart>
      <isForeground>false</isForeground>
      <backgroundImage>WaterwayB</backgroundImage>
      <offset x="0" y="0"/>
      <speed x="0" y="0"/>
      <tileHorizontally>false</tileHorizontally>
      <tileVertically>false</tileVertically>
      <stretch>true</stretch>
    </backgroundDef>
    <backgroundDef>
      <visibleOnRoomStart>false</visibleOnRoomStart>
      <isForeground>false</isForeground>
      <backgroundImage/>
      <offset x="0" y="0"/>
      <speed x="0" y="0"/>
      <tileHorizontally>true</tileHorizontally>
      <tileVertically>true</tileVertically>
      <stretch>false</stretch>
    </backgroundDef>
    <backgroundDef>
      <visibleOnRoomStart>false</visibleOnRoomStart>
      <isForeground>false</isForeground>
      <backgroundImage/>
      <offset x="0" y="0"/>
      <speed x="0" y="0"/>
      <tileHorizontally>true</tileHorizontally>
      <tileVertically>true</tileVertically>
      <stretch>false</stretch>
    </backgroundDef>
    <backgroundDef>
      <visibleOnRoomStart>false</visibleOnRoomStart>
      <isForeground>false</isForeground>
      <backgroundImage/>
      <offset x="0" y="0"/>
      <speed x="0" y="0"/>
      <tileHorizontally>true</tileHorizontally>
      <tileVertically>true</tileVertically>
      <stretch>false</stretch>
    </backgroundDef>
    <backgroundDef>
      <visibleOnRoomStart>false</visibleOnRoomStart>
      <isForeground>false</isForeground>
      <backgroundImage/>
      <offset x="0" y="0"/>
      <speed x="0" y="0"/>
      <tileHorizontally>true</tileHorizontally>
      <tileVertically>true</tileVertically>
      <stretch>false</stretch>
    </backgroundDef>
    <backgroundDef>
      <visibleOnRoomStart>false</visibleOnRoomStart>
      <isForeground>false</isForeground>
      <backgroundImage/>
      <offset x="0" y="0"/>
      <speed x="0" y="0"/>
      <tileHorizontally>true</tileHorizontally>
      <tileVertically>true</tileVertically>
      <stretch>false</stretch>
    </backgroundDef>
    <backgroundDef>
      <visibleOnRoomStart>false</visibleOnRoomStart>
      <isForeground>false</isForeground>
      <backgroundImage/>
      <offset x="0" y="0"/>
      <speed x="0" y="0"/>
      <tileHorizontally>true</tileHorizontally>
      <tileVertically>true</tileVertically>
      <stretch>false</stretch>
    </backgroundDef>
    <backgroundDef>
      <visibleOnRoomStart>false</visibleOnRoomStart>
      <isForeground>false</isForeground>
      <backgroundImage/>
      <offset x="0" y="0"/>
      <speed x="0" y="0"/>
      <tileHorizontally>true</tileHorizontally>
      <tileVertically>true</tileVertically>
      <stretch>false</stretch>
    </backgroundDef>
  </backgrounds>
  <enableViews>true</enableViews>
  <views>
    <view>
      <visibleOnRoomStart>true</visibleOnRoomStart>
      <viewInRoom height="600" width="800" x="0" y="0"/>
      <portOnScreen height="600" width="800" x="0" y="0"/>
      <objectFollowing hBorder="32" hSpeed="-1" vBorder="32" vSpeed="-1"/>
    </view>
    <view>
      <visibleOnRoomStart>false</visibleOnRoomStart>
      <viewInRoom height="480" width="640" x="0" y="0"/>
      <portOnScreen height="480" width="640" x="0" y="0"/>
      <objectFollowing hBorder="32" hSpeed="-1" vBorder="32" vSpeed="-1"/>
    </view>
    <view>
      <visibleOnRoomStart>false</visibleOnRoomStart>
      <viewInRoom height="480" width="640" x="0" y="0"/>
      <portOnScreen height="480" width="640" x="0" y="0"/>
      <objectFollowing hBorder="32" hSpeed="-1" vBorder="32" vSpeed="-1"/>
    </view>
    <view>
      <visibleOnRoomStart>false</visibleOnRoomStart>
      <viewInRoom height="480" width="640" x="0" y="0"/>
      <portOnScreen height="480" width="640" x="0" y="0"/>
      <objectFollowing hBorder="32" hSpeed="-1" vBorder="32" vSpeed="-1"/>
    </view>
    <view>
      <visibleOnRoomStart>false</visibleOnRoomStart>
      <viewInRoom height="480" width="640" x="0" y="0"/>
      <portOnScreen height="480" width="640" x="0" y="0"/>
      <objectFollowing hBorder="32" hSpeed="-1" vBorder="32" vSpeed="-1"/>
    </view>
    <view>
      <visibleOnRoomStart>false</visibleOnRoomStart>
      <viewInRoom height="480" width="640" x="0" y="0"/>
      <portOnScreen height="480" width="640" x="0" y="0"/>
      <objectFollowing hBorder="32" hSpeed="-1" vBorder="32" vSpeed="-1"/>
    </view>
    <view>
      <visibleOnRoomStart>false</visibleOnRoomStart>
      <viewInRoom height="480" width="640" x="0" y="0"/>
      <portOnScreen height="480" width="640" x="0" y="0"/>
      <objectFollowing hBorder="32" hSpeed="-1" vBorder="32" vSpeed="-1"/>
    </view>
    <view>
      <visibleOnRoomStart>false</visibleOnRoomStart>
      <viewInRoom height="480" width="640" x="0" y="0"/>
      <portOnScreen height="480" width="640" x="0" y="0"/>
      <objectFollowing hBorder="32" hSpeed="-1" vBorder="32" vSpeed="-1"/>
    </view>
  </views>
  <instances>
    <instance>
      <object>SpawnRoom</object>
      <position x="5370" y="1428"/>
      <creationCode/>
      <locked>false</locked>
    </instance>
    <instance>
      <object>HealingCabinet</object>
      <position x="510" y="942"/>
      <creationCode/>
      <locked>false</locked>
    </instance>
    <instance>
      <object>HealingCabinet</object>
      <position x="546" y="942"/>
      <creationCode/>
      <locked>false</locked>
    </instance>
    <instance>
      <object>SpawnPointRed</object>
      <position x="600" y="948"/>
      <creationCode/>
      <locked>false</locked>
    </instance>
    <instance>
      <object>SpawnPointRed</object>
      <position x="636" y="948"/>
      <creationCode/>
      <locked>false</locked>
    </instance>
    <instance>
      <object>SpawnPointRed</object>
      <position x="672" y="948"/>
      <creationCode/>
      <locked>false</locked>
    </instance>
    <instance>
      <object>SpawnPointRed</object>
      <position x="714" y="948"/>
      <creationCode/>
      <locked>false</locked>
    </instance>
    <instance>
      <object>SpawnPointRed</object>
      <position x="756" y="948"/>
      <creationCode/>
      <locked>false</locked>
    </instance>
    <instance>
      <object>RedTeamGate</object>
      <position x="792" y="942"/>
      <creationCode/>
      <locked>false</locked>
    </instance>
    <instance>
      <object>RedTeamGate</object>
      <position x="792" y="912"/>
      <creationCode/>
      <locked>false</locked>
    </instance>
    <instance>
      <object>RedTeamGate</object>
      <position x="798" y="912"/>
      <creationCode/>
      <locked>false</locked>
    </instance>
    <instance>
      <object>RedTeamGate</object>
      <position x="798" y="942"/>
      <creationCode/>
      <locked>false</locked>
    </instance>
    <instance>
      <object>RedTeamGate</object>
      <position x="804" y="912"/>
      <creationCode/>
      <locked>false</locked>
    </instance>
    <instance>
      <object>RedTeamGate</object>
      <position x="804" y="942"/>
      <creationCode/>
      <locked>false</locked>
    </instance>
    <instance>
      <object>SpawnRoom</object>
      <position x="498" y="960"/>
      <creationCode/>
      <locked>false</locked>
    </instance>
    <instance>
      <object>SpawnRoom</object>
      <position x="498" y="918"/>
      <creationCode/>
      <locked>false</locked>
    </instance>
    <instance>
      <object>SpawnRoom</object>
      <position x="540" y="960"/>
      <creationCode/>
      <locked>false</locked>
    </instance>
    <instance>
      <object>SpawnRoom</object>
      <position x="582" y="960"/>
      <creationCode/>
      <locked>false</locked>
    </instance>
    <instance>
      <object>SpawnRoom</object>
      <position x="624" y="960"/>
      <creationCode/>
      <locked>false</locked>
    </instance>
    <instance>
      <object>SpawnRoom</object>
      <position x="666" y="960"/>
      <creationCode/>
      <locked>false</locked>
    </instance>
    <instance>
      <object>SpawnRoom</object>
      <position x="708" y="960"/>
      <creationCode/>
      <locked>false</locked>
    </instance>
    <instance>
      <object>SpawnRoom</object>
      <position x="750" y="960"/>
      <creationCode/>
      <locked>false</locked>
    </instance>
    <instance>
      <object>SpawnRoom</object>
      <position x="750" y="918"/>
      <creationCode/>
      <locked>false</locked>
    </instance>
    <instance>
      <object>SpawnRoom</object>
      <position x="708" y="918"/>
      <creationCode/>
      <locked>false</locked>
    </instance>
    <instance>
      <object>SpawnRoom</object>
      <position x="666" y="918"/>
      <creationCode/>
      <locked>false</locked>
    </instance>
    <instance>
      <object>SpawnRoom</object>
      <position x="624" y="918"/>
      <creationCode/>
      <locked>false</locked>
    </instance>
    <instance>
      <object>SpawnRoom</object>
      <position x="582" y="918"/>
      <creationCode/>
      <locked>false</locked>
    </instance>
    <instance>
      <object>SpawnRoom</object>
      <position x="540" y="918"/>
      <creationCode/>
      <locked>false</locked>
    </instance>
    <instance>
      <object>HealingCabinet</object>
      <position x="1278" y="1014"/>
      <creationCode/>
      <locked>false</locked>
    </instance>
    <instance>
      <object>HealingCabinet</object>
      <position x="1314" y="1014"/>
      <creationCode/>
      <locked>false</locked>
    </instance>
    <instance>
      <object>RedTeamGate</object>
      <position x="1128" y="984"/>
      <creationCode/>
      <locked>false</locked>
    </instance>
    <instance>
      <object>RedTeamGate</object>
      <position x="1128" y="1014"/>
      <creationCode/>
      <locked>false</locked>
    </instance>
    <instance>
      <object>RedTeamGate</object>
      <position x="1134" y="984"/>
      <creationCode/>
      <locked>false</locked>
    </instance>
    <instance>
      <object>RedTeamGate</object>
      <position x="1134" y="1014"/>
      <creationCode/>
      <locked>false</locked>
    </instance>
    <instance>
      <object>RedTeamGate</object>
      <position x="1140" y="984"/>
      <creationCode/>
      <locked>false</locked>
    </instance>
    <instance>
      <object>RedTeamGate</object>
      <position x="1140" y="1014"/>
      <creationCode/>
      <locked>false</locked>
    </instance>
    <instance>
      <object>RedTeamGate</object>
      <position x="1446" y="870"/>
      <creationCode/>
      <locked>false</locked>
    </instance>
    <instance>
      <object>RedTeamGate</object>
      <position x="1446" y="900"/>
      <creationCode/>
      <locked>false</locked>
    </instance>
    <instance>
      <object>RedTeamGate</object>
      <position x="1440" y="876"/>
      <creationCode/>
      <locked>false</locked>
    </instance>
    <instance>
      <object>RedTeamGate</object>
      <position x="1440" y="918"/>
      <creationCode/>
      <locked>false</locked>
    </instance>
    <instance>
      <object>RedTeamGate</object>
      <position x="1434" y="882"/>
      <creationCode/>
      <locked>false</locked>
    </instance>
    <instance>
      <object>RedTeamGate</object>
      <position x="1434" y="924"/>
      <creationCode/>
      <locked>false</locked>
    </instance>
    <instance>
      <object>SpawnPointRed</object>
      <position x="1164" y="1020"/>
      <creationCode/>
      <locked>false</locked>
    </instance>
    <instance>
      <object>SpawnPointRed</object>
      <position x="1188" y="1020"/>
      <creationCode/>
      <locked>false</locked>
    </instance>
    <instance>
      <object>SpawnPointRed</object>
      <position x="1248" y="1020"/>
      <creationCode/>
      <locked>false</locked>
    </instance>
    <instance>
      <object>SpawnPointRed</object>
      <position x="1218" y="1020"/>
      <creationCode/>
      <locked>false</locked>
    </instance>
    <instance>
      <object>SpawnRoom</object>
      <position x="1146" y="1032"/>
      <creationCode/>
      <locked>false</locked>
    </instance>
    <instance>
      <object>SpawnRoom</object>
      <position x="1188" y="1032"/>
      <creationCode/>
      <locked>false</locked>
    </instance>
    <instance>
      <object>SpawnRoom</object>
      <position x="1230" y="1032"/>
      <creationCode/>
      <locked>false</locked>
    </instance>
    <instance>
      <object>SpawnRoom</object>
      <position x="1272" y="1032"/>
      <creationCode/>
      <locked>false</locked>
    </instance>
    <instance>
      <object>SpawnRoom</object>
      <position x="1314" y="1032"/>
      <creationCode/>
      <locked>false</locked>
    </instance>
    <instance>
      <object>SpawnRoom</object>
      <position x="1344" y="1026"/>
      <creationCode/>
      <locked>false</locked>
    </instance>
    <instance>
      <object>SpawnRoom</object>
      <position x="1374" y="996"/>
      <creationCode/>
      <locked>false</locked>
    </instance>
    <instance>
      <object>SpawnRoom</object>
      <position x="1404" y="966"/>
      <creationCode/>
      <locked>false</locked>
    </instance>
    <instance>
      <object>SpawnRoom</object>
      <position x="1146" y="990"/>
      <creationCode/>
      <locked>false</locked>
    </instance>
    <instance>
      <object>SpawnRoom</object>
      <position x="1188" y="990"/>
      <creationCode/>
      <locked>false</locked>
    </instance>
    <instance>
      <object>SpawnRoom</object>
      <position x="1230" y="990"/>
      <creationCode/>
      <locked>false</locked>
    </instance>
    <instance>
      <object>SpawnRoom</object>
      <position x="1272" y="990"/>
      <creationCode/>
      <locked>false</locked>
    </instance>
    <instance>
      <object>SpawnRoom</object>
      <position x="1314" y="990"/>
      <creationCode/>
      <locked>false</locked>
    </instance>
    <instance>
      <object>SpawnRoom</object>
      <position x="1344" y="984"/>
      <creationCode/>
      <locked>false</locked>
    </instance>
    <instance>
      <object>SpawnRoom</object>
      <position x="1368" y="960"/>
      <creationCode/>
      <locked>false</locked>
    </instance>
    <instance>
      <object>SpawnRoom</object>
      <position x="1398" y="924"/>
      <creationCode/>
      <locked>false</locked>
    </instance>
    <instance>
      <object>SpawnPointBlue</object>
      <position x="5658" y="948"/>
      <creationCode/>
      <locked>false</locked>
    </instance>
    <instance>
      <object>SpawnPointBlue</object>
      <position x="5628" y="948"/>
      <creationCode/>
      <locked>false</locked>
    </instance>
    <instance>
      <object>SpawnPointBlue</object>
      <position x="5592" y="948"/>
      <creationCode/>
      <locked>false</locked>
    </instance>
    <instance>
      <object>SpawnPointBlue</object>
      <position x="5556" y="948"/>
      <creationCode/>
      <locked>false</locked>
    </instance>
    <instance>
      <object>SpawnPointBlue</object>
      <position x="5514" y="948"/>
      <creationCode/>
      <locked>false</locked>
    </instance>
    <instance>
      <object>BlueTeamGate</object>
      <position x="5460" y="912"/>
      <creationCode/>
      <locked>false</locked>
    </instance>
    <instance>
      <object>BlueTeamGate</object>
      <position x="5460" y="942"/>
      <creationCode/>
      <locked>false</locked>
    </instance>
    <instance>
      <object>BlueTeamGate</object>
      <position x="5466" y="912"/>
      <creationCode/>
      <locked>false</locked>
    </instance>
    <instance>
      <object>BlueTeamGate</object>
      <position x="5466" y="942"/>
      <creationCode/>
      <locked>false</locked>
    </instance>
    <instance>
      <object>BlueTeamGate</object>
      <position x="5472" y="912"/>
      <creationCode/>
      <locked>false</locked>
    </instance>
    <instance>
      <object>BlueTeamGate</object>
      <position x="5472" y="942"/>
      <creationCode/>
      <locked>false</locked>
    </instance>
    <instance>
      <object>BlueTeamGate</object>
      <position x="5130" y="984"/>
      <creationCode/>
      <locked>false</locked>
    </instance>
    <instance>
      <object>BlueTeamGate</object>
      <position x="5130" y="1014"/>
      <creationCode/>
      <locked>false</locked>
    </instance>
    <instance>
      <object>BlueTeamGate</object>
      <position x="5136" y="984"/>
      <creationCode/>
      <locked>false</locked>
    </instance>
    <instance>
      <object>BlueTeamGate</object>
      <position x="5136" y="1014"/>
      <creationCode/>
      <locked>false</locked>
    </instance>
    <instance>
      <object>BlueTeamGate</object>
      <position x="5124" y="984"/>
      <creationCode/>
      <locked>false</locked>
    </instance>
    <instance>
      <object>BlueTeamGate</object>
      <position x="5124" y="1014"/>
      <creationCode/>
      <locked>false</locked>
    </instance>
    <instance>
      <object>BlueTeamGate</object>
      <position x="4818" y="870"/>
      <creationCode/>
      <locked>false</locked>
    </instance>
    <instance>
      <object>BlueTeamGate</object>
      <position x="4818" y="912"/>
      <creationCode/>
      <locked>false</locked>
    </instance>
    <instance>
      <object>BlueTeamGate</object>
      <position x="4824" y="870"/>
      <creationCode/>
      <locked>false</locked>
    </instance>
    <instance>
      <object>BlueTeamGate</object>
      <position x="4824" y="918"/>
      <creationCode/>
      <locked>false</locked>
    </instance>
    <instance>
      <object>BlueTeamGate</object>
      <position x="4830" y="882"/>
      <creationCode/>
      <locked>false</locked>
    </instance>
    <instance>
      <object>BlueTeamGate</object>
      <position x="4830" y="924"/>
      <creationCode/>
      <locked>false</locked>
    </instance>
    <instance>
      <object>HealingCabinet</object>
      <position x="5694" y="948"/>
      <creationCode/>
      <locked>false</locked>
    </instance>
    <instance>
      <object>HealingCabinet</object>
      <position x="5730" y="948"/>
      <creationCode/>
      <locked>false</locked>
    </instance>
    <instance>
      <object>SpawnPointBlue</object>
      <position x="5094" y="1020"/>
      <creationCode/>
      <locked>false</locked>
    </instance>
    <instance>
      <object>SpawnPointBlue</object>
      <position x="5064" y="1020"/>
      <creationCode/>
      <locked>false</locked>
    </instance>
    <instance>
      <object>SpawnPointBlue</object>
      <position x="5034" y="1020"/>
      <creationCode/>
      <locked>false</locked>
    </instance>
    <instance>
      <object>SpawnPointBlue</object>
      <position x="5004" y="1020"/>
      <creationCode/>
      <locked>false</locked>
    </instance>
    <instance>
      <object>HealingCabinet</object>
      <position x="4926" y="1020"/>
      <creationCode/>
      <locked>false</locked>
    </instance>
    <instance>
      <object>HealingCabinet</object>
      <position x="4962" y="1020"/>
      <creationCode/>
      <locked>false</locked>
    </instance>
    <instance>
      <object>SpawnRoom</object>
      <position x="5478" y="960"/>
      <creationCode/>
      <locked>false</locked>
    </instance>
    <instance>
      <object>SpawnRoom</object>
      <position x="5520" y="960"/>
      <creationCode/>
      <locked>false</locked>
    </instance>
    <instance>
      <object>SpawnRoom</object>
      <position x="5562" y="960"/>
      <creationCode/>
      <locked>false</locked>
    </instance>
    <instance>
      <object>SpawnRoom</object>
      <position x="5604" y="960"/>
      <creationCode/>
      <locked>false</locked>
    </instance>
    <instance>
      <object>SpawnRoom</object>
      <position x="5646" y="960"/>
      <creationCode/>
      <locked>false</locked>
    </instance>
    <instance>
      <object>SpawnRoom</object>
      <position x="5688" y="960"/>
      <creationCode/>
      <locked>false</locked>
    </instance>
    <instance>
      <object>SpawnRoom</object>
      <position x="5730" y="960"/>
      <creationCode/>
      <locked>false</locked>
    </instance>
    <instance>
      <object>SpawnRoom</object>
      <position x="5730" y="918"/>
      <creationCode/>
      <locked>false</locked>
    </instance>
    <instance>
      <object>SpawnRoom</object>
      <position x="5688" y="918"/>
      <creationCode/>
      <locked>false</locked>
    </instance>
    <instance>
      <object>SpawnRoom</object>
      <position x="5646" y="918"/>
      <creationCode/>
      <locked>false</locked>
    </instance>
    <instance>
      <object>SpawnRoom</object>
      <position x="5604" y="918"/>
      <creationCode/>
      <locked>false</locked>
    </instance>
    <instance>
      <object>SpawnRoom</object>
      <position x="5562" y="918"/>
      <creationCode/>
      <locked>false</locked>
    </instance>
    <instance>
      <object>SpawnRoom</object>
      <position x="5520" y="918"/>
      <creationCode/>
      <locked>false</locked>
    </instance>
    <instance>
      <object>SpawnRoom</object>
      <position x="5478" y="918"/>
      <creationCode/>
      <locked>false</locked>
    </instance>
    <instance>
      <object>SpawnRoom</object>
      <position x="5082" y="1032"/>
      <creationCode/>
      <locked>false</locked>
    </instance>
    <instance>
      <object>SpawnRoom</object>
      <position x="5040" y="1032"/>
      <creationCode/>
      <locked>false</locked>
    </instance>
    <instance>
      <object>SpawnRoom</object>
      <position x="4998" y="1032"/>
      <creationCode/>
      <locked>false</locked>
    </instance>
    <instance>
      <object>SpawnRoom</object>
      <position x="4956" y="1032"/>
      <creationCode/>
      <locked>false</locked>
    </instance>
    <instance>
      <object>SpawnRoom</object>
      <position x="4914" y="1032"/>
      <creationCode/>
      <locked>false</locked>
    </instance>
    <instance>
      <object>SpawnRoom</object>
      <position x="4890" y="1026"/>
      <creationCode/>
      <locked>false</locked>
    </instance>
    <instance>
      <object>SpawnRoom</object>
      <position x="4866" y="1002"/>
      <creationCode/>
      <locked>false</locked>
    </instance>
    <instance>
      <object>SpawnRoom</object>
      <position x="4842" y="978"/>
      <creationCode/>
      <locked>false</locked>
    </instance>
    <instance>
      <object>SpawnRoom</object>
      <position x="4824" y="954"/>
      <creationCode/>
      <locked>false</locked>
    </instance>
    <instance>
      <object>SpawnRoom</object>
      <position x="5082" y="990"/>
      <creationCode/>
      <locked>false</locked>
    </instance>
    <instance>
      <object>SpawnRoom</object>
      <position x="5040" y="990"/>
      <creationCode/>
      <locked>false</locked>
    </instance>
    <instance>
      <object>SpawnRoom</object>
      <position x="4998" y="990"/>
      <creationCode/>
      <locked>false</locked>
    </instance>
    <instance>
      <object>SpawnRoom</object>
      <position x="4956" y="990"/>
      <creationCode/>
      <locked>false</locked>
    </instance>
    <instance>
      <object>SpawnRoom</object>
      <position x="4914" y="990"/>
      <creationCode/>
      <locked>false</locked>
    </instance>
    <instance>
      <object>SpawnRoom</object>
      <position x="4890" y="984"/>
      <creationCode/>
      <locked>false</locked>
    </instance>
    <instance>
      <object>SpawnRoom</object>
      <position x="4872" y="960"/>
      <creationCode/>
      <locked>false</locked>
    </instance>
    <instance>
      <object>SpawnRoom</object>
      <position x="4854" y="936"/>
      <creationCode/>
      <locked>false</locked>
    </instance>
    <instance>
      <object>SpawnRoom</object>
      <position x="4836" y="912"/>
      <creationCode/>
      <locked>false</locked>
    </instance>
    <instance>
      <object>IntelligenceBaseRed</object>
      <position x="996" y="1014"/>
      <creationCode/>
      <locked>false</locked>
    </instance>
    <instance>
      <object>IntelligenceBaseBlue</object>
      <position x="5274" y="1014"/>
      <creationCode/>
      <locked>false</locked>
    </instance>
  </instances>
  <tiles/>
  <editorSettings remember="false"/>
</room>
